odc/testing/__init__.py
odc/testing/database.py
pytest_odc-0.3.0.dist-info/LICENSE
pytest_odc-0.3.0.dist-info/METADATA
pytest_odc-0.3.0.dist-info/WHEEL
pytest_odc-0.3.0.dist-info/entry_points.txt
pytest_odc-0.3.0.dist-info/top_level.txt
pytest_odc-0.3.0.dist-info/RECORD
