Metadata-Version: 2.1
Name: pytest-odc
Version: 0.3.0
Summary: A pytest plugin for simplifying ODC database tests
Author: Open Data Cube
Project-URL: Homepage, https://www.opendatacube.org/
Project-URL: Repository, https://github.com/opendatacube/pytest-odc
Classifier: Development Status :: 4 - Beta
Classifier: Framework :: Pytest
Classifier: Intended Audience :: Developers
Classifier: Topic :: Software Development :: Testing
Classifier: Programming Language :: Python
Classifier: Programming Language :: Python :: 3
Classifier: Programming Language :: Python :: 3.8
Classifier: Programming Language :: Python :: 3.9
Classifier: Programming Language :: Python :: 3.10
Classifier: Programming Language :: Python :: 3 :: Only
Classifier: Programming Language :: Python :: Implementation :: CPython
Classifier: Programming Language :: Python :: Implementation :: PyPy
Classifier: Operating System :: OS Independent
Classifier: License :: OSI Approved :: Apache Software License
Requires-Python: >=3.8
License-File: LICENSE
Requires-Dist: pytest (>=3.5.0)
Requires-Dist: docker
